pyshovels/__init__.py
pyshovels/client.py
pyshovels-0.0.2.dist-info/LICENSE
pyshovels-0.0.2.dist-info/METADATA
pyshovels-0.0.2.dist-info/WHEEL
pyshovels-0.0.2.dist-info/RECORD
