Metadata-Version: 2.3
Name: pyshovels
Version: 0.0.2
Summary: Unofficial Python package designed to interact with the Shovels API
Author: Nicolas Fonteyne
Author-email: nicolasakfonteyne@gmail.com
Requires-Python: >=3.9
Classifier: Programming Language :: Python :: 3
Classifier: License :: OSI Approved :: MIT License
Classifier: Operating System :: OS Independent
Requires-Dist: pandas (>=2.0.3)
Requires-Dist: requests (>=2.32.3)
Project-URL: Bug Tracker, https://github.com/nicolasakf/pyshovels/issues
Project-URL: Homepage, https://github.com/nicolasakf/pyshovels
